holos/__main__.py
holos/client/__init__.py
holos/client/main.py
holos_client-0.1.0.dist-info/METADATA
holos_client-0.1.0.dist-info/WHEEL
holos_client-0.1.0.dist-info/entry_points.txt
holos_client-0.1.0.dist-info/RECORD
