Metadata-Version: 2.1
Name: holos-client
Version: 0.1.0
Summary: Holos platform manager command line utility
Author: Holos Contributors
Author-email: holos-run@openinfrastructure.co
Requires-Python: >=3.11,<4.0
Classifier: Programming Language :: Python :: 3
Classifier: Programming Language :: Python :: 3.11
Requires-Dist: httpx (>=0.23.3,<0.24.0)
Requires-Dist: poetry (>=1.5.1,<2.0.0)
Requires-Dist: rich (>=13.3.5,<14.0.0)
Requires-Dist: typer[all] (>=0.9.0,<0.10.0)
